dymaxionlabs/__init__.py
dymaxionlabs/file.py
dymaxionlabs/files.py
dymaxionlabs/model.py
dymaxionlabs/models.py
dymaxionlabs/utils.py
dymaxionlabs-0.1.1.dist-info/AUTHORS.rst
dymaxionlabs-0.1.1.dist-info/LICENSE.txt
dymaxionlabs-0.1.1.dist-info/METADATA
dymaxionlabs-0.1.1.dist-info/WHEEL
dymaxionlabs-0.1.1.dist-info/top_level.txt
dymaxionlabs-0.1.1.dist-info/RECORD
