Metadata-Version: 2.1
Name: dymaxionlabs
Version: 0.1.1
Summary: Python client for Dymaxion Labs API
Home-page: https://github.com/pyscaffold/pyscaffold/
Author: Dymaxion Labs
Author-email: contact@dymaxionlabs.com
License: apache-2.0
Project-URL: Documentation, https://pyscaffold.org/
Platform: any
Classifier: Development Status :: 4 - Beta
Classifier: Programming Language :: Python
Requires-Dist: requests
Provides-Extra: testing
Requires-Dist: pytest ; extra == 'testing'
Requires-Dist: pytest-cov ; extra == 'testing'
